pytest_case/__init__.py
pytest_case/case.py
pytest_case/consts.py
pytest_case/types.py
pytest_case/utils/__init__.py
pytest_case/utils/case_utils.py
pytest_case/utils/func_utils.py
pytest_case-1.0.0.dist-info/LICENSE
pytest_case-1.0.0.dist-info/METADATA
pytest_case-1.0.0.dist-info/WHEEL
pytest_case-1.0.0.dist-info/RECORD
