Metadata-Version: 2.1
Name: pytest_case
Version: 1.0.0
Summary: A clean, modern, wrapper for pytest.mark.parametrize
Home-page: https://github.com/eitanwass/pytest-case
License: Apache-2.0
Keywords: pytest,parametrize,case,test
Author: Ethan Wass
Author-email: eitanwass@gmail.com
Requires-Python: >=3.8,<4.0
Classifier: License :: OSI Approved :: Apache Software License
Classifier: Programming Language :: Python :: 3
Classifier: Programming Language :: Python :: 3.8
Classifier: Programming Language :: Python :: 3.9
Classifier: Programming Language :: Python :: 3.10
Classifier: Programming Language :: Python :: 3.11
Classifier: Programming Language :: Python :: 3.12
Classifier: Programming Language :: Python :: 3.13
Requires-Dist: pytest (>=8.3.3,<9.0.0)
Project-URL: Repository, https://github.com/eitanwass/pytest-case
